ipyc/__init__.py
ipyc/asynchronous.py
ipyc/blocking.py
ipyc/headers.py
ipyc/links.py
ipyc/packets.py
ipyc/serialization.py
IPyC-1.1.1.dist-info/LICENSE
IPyC-1.1.1.dist-info/METADATA
IPyC-1.1.1.dist-info/WHEEL
IPyC-1.1.1.dist-info/top_level.txt
IPyC-1.1.1.dist-info/RECORD
